{
  "ic_mean": 0.0097,
  "rank_ic": 0.0097,
  "ir": 0.0951,
  "ic_t_stat": 1.2,
  "ic_significant": false,
  "ic_positive_pct": 0.503,
  "monotonicity": 0.0,
  "long_short_total_return": 0.0447,
  "long_short_annual_return": 0.0139,
  "long_short_sharpe": 0.1813,
  "long_short_mdd": -0.1062,
  "turnover_mean": 0.5,
  "group_returns_annualized": [
    0.0902,
    0.1048,
    0.0702,
    0.0574,
    0.1127
  ],
  "group_sharpe": [
    0.454,
    0.522,
    0.42,
    0.354,
    0.539
  ],
  "group_mdd": [
    -0.2684,
    -0.1828,
    -0.1941,
    -0.2576,
    -0.2462
  ]
}